TTS_ka/__init__.py
TTS_ka/__main__.py
TTS_ka/audio.py
TTS_ka/chunking.py
TTS_ka/fast_audio.py
TTS_ka/help_system.py
TTS_ka/main.py
TTS_ka/not_reading.py
TTS_ka/parallel.py
TTS_ka/rich_progress.py
TTS_ka/simple_help.py
TTS_ka/streaming_player.py
TTS_ka/ultra_fast.py
tts_ka-1.4.1.dist-info/licenses/LICENSE
tts_ka-1.4.1.dist-info/METADATA
tts_ka-1.4.1.dist-info/WHEEL
tts_ka-1.4.1.dist-info/entry_points.txt
tts_ka-1.4.1.dist-info/top_level.txt
tts_ka-1.4.1.dist-info/RECORD
