Metadata-Version: 2.4
Name: TTS_ka
Version: 1.4.1
Summary: A simple text to speech program using edge-tts library
Author-email: David Chincharashvili <davidchincharashvili@gmail.com>
Project-URL: Homepage, https://github.com/DavidTbilisi/TTS.git
Classifier: Programming Language :: Python :: 3
Classifier: License :: OSI Approved :: MIT License
Classifier: Operating System :: OS Independent
Requires-Python: >=3.6
License-File: LICENSE
Requires-Dist: edge-tts>=6.1.9
Requires-Dist: pydub>=0.25.1
Requires-Dist: tqdm>=4.65.0
Requires-Dist: pyperclip>=1.8.2
Requires-Dist: httpx>=0.28.1
Provides-Extra: test
Requires-Dist: pytest>=7.0.0; extra == "test"
Requires-Dist: pytest-asyncio>=0.21.0; extra == "test"
Requires-Dist: pytest-cov>=4.0.0; extra == "test"
Requires-Dist: pytest-mock>=3.10.0; extra == "test"
Requires-Dist: coverage[toml]>=7.0.0; extra == "test"
Provides-Extra: dev
Requires-Dist: pytest>=7.0.0; extra == "dev"
Requires-Dist: pytest-asyncio>=0.21.0; extra == "dev"
Requires-Dist: pytest-cov>=4.0.0; extra == "dev"
Requires-Dist: pytest-mock>=3.10.0; extra == "dev"
Requires-Dist: coverage[toml]>=7.0.0; extra == "dev"
Requires-Dist: black>=23.0.0; extra == "dev"
Requires-Dist: flake8>=6.0.0; extra == "dev"
Requires-Dist: mypy>=1.0.0; extra == "dev"
Dynamic: license-file
